tests/__init__.py
tests/test_benchmarks.py
tests/test_core.py
komlos_optimal-0.1.0.dist-info/LICENSE
komlos_optimal-0.1.0.dist-info/METADATA
komlos_optimal-0.1.0.dist-info/WHEEL
komlos_optimal-0.1.0.dist-info/top_level.txt
komlos_optimal-0.1.0.dist-info/RECORD
