Metadata-Version: 2.1
Name: komlos_optimal
Version: 0.1.0
Summary: Library for optimal subsequence computation inspired by Komlós conjecture.
Home-page: https://github.com/ANTHONY-OLEVESTER/komlos_optimal
Author: Anthony Olevester
Author-email: olevester.joram123@gmail.com
Classifier: Programming Language :: Python :: 3
Classifier: License :: OSI Approved :: MIT License
Classifier: Operating System :: OS Independent
Requires-Python: >=3.6
License-File: LICENSE
Requires-Dist: numpy
